met_jobs/__init__.py
met_jobs/database.csv
met_jobs/database.py
met_jobs/search.py
met_jobs/style.py
met_jobs-0.3.data/scripts/create_db
met_jobs-0.3.data/scripts/search_met
met_jobs-0.3.dist-info/LICENSE
met_jobs-0.3.dist-info/METADATA
met_jobs-0.3.dist-info/WHEEL
met_jobs-0.3.dist-info/top_level.txt
met_jobs-0.3.dist-info/RECORD
