Metadata-Version: 2.1
Name: met-jobs
Version: 0.3
Summary: Search engine for the jobs advertised via the Met-jobs mailing list
Home-page: https://github.com/gcaria/met-jobs
Author: Giacomo Caria
Author-email: giacomo.caria@gmail.com
License: MIT
Platform: UNKNOWN
Classifier: Development Status :: 4 - Beta
Classifier: Operating System :: OS Independent
Classifier: Intended Audience :: Science/Research
Classifier: License :: OSI Approved :: MIT License
Classifier: Programming Language :: Python
Classifier: Programming Language :: Python :: 3
Classifier: Programming Language :: Python :: 3.8
Classifier: Programming Language :: Python :: 3.9
Requires-Python: >=3.8
License-File: LICENSE
Requires-Dist: pandas (>=1.2.1)
Requires-Dist: scikit-learn (>=0.24.1)
Provides-Extra: scrape
Requires-Dist: requests ; extra == 'scrape'
Requires-Dist: beautifulsoup4 ; extra == 'scrape'
Requires-Dist: tqdm ; extra == 'scrape'
Requires-Dist: lxml ; extra == 'scrape'
